Metadata-Version: 2.1
Name: manim
Version: 0.17.1
Summary: Animation engine for explanatory math videos.
Home-page: https://www.manim.community/
License: MIT
Author: The Manim Community Developers
Author-email: contact@manim.community
Requires-Python: >=3.8,<3.12
Classifier: Development Status :: 4 - Beta
Classifier: License :: OSI Approved :: MIT License
Classifier: Natural Language :: English
Classifier: Programming Language :: Python :: 3
Classifier: Programming Language :: Python :: 3.8
Classifier: Programming Language :: Python :: 3.9
Classifier: Programming Language :: Python :: 3.10
Classifier: Programming Language :: Python :: 3.11
Classifier: Programming Language :: Python :: 3.10
Classifier: Programming Language :: Python :: 3.7
Classifier: Programming Language :: Python :: 3.8
Classifier: Programming Language :: Python :: 3.9
Classifier: Topic :: Multimedia :: Graphics
Classifier: Topic :: Multimedia :: Video
Classifier: Topic :: Scientific/Engineering
Provides-Extra: gui
Provides-Extra: jupyterlab
Requires-Dist: Pillow (>=9.1,<10.0)
Requires-Dist: Pygments (>=2.10.0,<3.0.0)
Requires-Dist: backports.cached-property (>=1.0.1,<2.0.0); python_version < "3.8"
Requires-Dist: click (>=7.2,<=9.0)
Requires-Dist: click-default-group (>=1.2.2,<2.0.0)
Requires-Dist: cloup (>=0.13.0,<0.14.0)
Requires-Dist: colour (>=0.1.5,<0.2.0)
Requires-Dist: dearpygui (>=1.3.1,<2.0.0); extra == "gui"
Requires-Dist: decorator (>=5.0.7,<6.0.0)
Requires-Dist: importlib-metadata (>=4.10.0,<5.0.0); python_version < "3.8"
Requires-Dist: isosurfaces (==0.1.0)
Requires-Dist: jupyterlab (>=3.0,<4.0); extra == "jupyterlab"
Requires-Dist: manimpango (>=0.4.0.post0,<0.5.0)
Requires-Dist: mapbox-earcut (>=1.0.0,<2.0.0)
Requires-Dist: moderngl (>=5.6.3,<6.0.0)
Requires-Dist: moderngl-window (>=2.3.0,<3.0.0)
Requires-Dist: networkx (>=2.5,<3.0)
Requires-Dist: notebook (>=6.4,<7.0); extra == "jupyterlab"
Requires-Dist: numpy (>=1.19,<2.0)
Requires-Dist: pycairo (>=1.21,<2.0)
Requires-Dist: pydub (>=0.25.1,<0.26.0)
Requires-Dist: requests (>=2.26.0,<3.0.0)
Requires-Dist: rich (>=6.0,!=12.0.0)
Requires-Dist: scipy (>=1.7.3,<2.0.0)
Requires-Dist: screeninfo (>=0.8,<0.9)
Requires-Dist: skia-pathops (>=0.7.0,<0.8.0)
Requires-Dist: srt (>=3.5.0,<4.0.0)
Requires-Dist: svgelements (>=1.8.0,<2.0.0)
Requires-Dist: tqdm (>=4.62.3,<5.0.0)
Requires-Dist: watchdog (>=2.1.6,<3.0.0)
Project-URL: Bug Tracker, https://github.com/ManimCommunity/manim/issues
Project-URL: Changelog, https://docs.manim.community/en/stable/changelog.html
Project-URL: Documentation, https://docs.manim.community/
Project-URL: Discord, https://www.manim.community/discord/
Project-URL: Repository, https://github.com/manimcommunity/manim
Project-URL: Twitter, https://twitter.com/manim_community
